setup.py
rancher_agent_registration/__init__.py
rancher_agent_registration/cli.py
rancher_agent_registration.egg-info/PKG-INFO
rancher_agent_registration.egg-info/SOURCES.txt
rancher_agent_registration.egg-info/dependency_links.txt
rancher_agent_registration.egg-info/entry_points.txt
rancher_agent_registration.egg-info/not-zip-safe
rancher_agent_registration.egg-info/requires.txt
rancher_agent_registration.egg-info/top_level.txt