Metadata-Version: 1.0
Name: rancher-agent-registration
Version: 1.1
Summary: Command line tool to register the current host with your Rancher server
Home-page: https://github.com/cdrx/rancher-host-registration
Author: Chris Rose
Author-email: UNKNOWN
License: MIT
Platform: UNKNOWN
